ynab_api/__init__.py
ynab_api/api_client.py
ynab_api/configuration.py
ynab_api/exceptions.py
ynab_api/model_utils.py
ynab_api/rest.py
ynab_api/api/__init__.py
ynab_api/api/accounts_api.py
ynab_api/api/budgets_api.py
ynab_api/api/categories_api.py
ynab_api/api/deprecated_api.py
ynab_api/api/months_api.py
ynab_api/api/payee_locations_api.py
ynab_api/api/payees_api.py
ynab_api/api/scheduled_transactions_api.py
ynab_api/api/transactions_api.py
ynab_api/api/user_api.py
ynab_api/apis/__init__.py
ynab_api/model/__init__.py
ynab_api/model/account.py
ynab_api/model/account_response.py
ynab_api/model/account_response_data.py
ynab_api/model/accounts_response.py
ynab_api/model/accounts_response_data.py
ynab_api/model/budget_detail.py
ynab_api/model/budget_detail_all_of.py
ynab_api/model/budget_detail_response.py
ynab_api/model/budget_detail_response_data.py
ynab_api/model/budget_settings.py
ynab_api/model/budget_settings_response.py
ynab_api/model/budget_settings_response_data.py
ynab_api/model/budget_summary.py
ynab_api/model/budget_summary_response.py
ynab_api/model/budget_summary_response_data.py
ynab_api/model/bulk_response.py
ynab_api/model/bulk_response_data.py
ynab_api/model/bulk_response_data_bulk.py
ynab_api/model/bulk_transactions.py
ynab_api/model/categories_response.py
ynab_api/model/categories_response_data.py
ynab_api/model/category.py
ynab_api/model/category_group.py
ynab_api/model/category_group_with_categories.py
ynab_api/model/category_group_with_categories_all_of.py
ynab_api/model/category_response.py
ynab_api/model/category_response_data.py
ynab_api/model/currency_format.py
ynab_api/model/date_format.py
ynab_api/model/error_detail.py
ynab_api/model/error_response.py
ynab_api/model/hybrid_transaction.py
ynab_api/model/hybrid_transaction_all_of.py
ynab_api/model/hybrid_transactions_response.py
ynab_api/model/hybrid_transactions_response_data.py
ynab_api/model/month_detail.py
ynab_api/model/month_detail_all_of.py
ynab_api/model/month_detail_response.py
ynab_api-2.0.2.dist-info/METADATA
ynab_api-2.0.2.dist-info/WHEEL
ynab_api-2.0.2.dist-info/top_level.txt
ynab_api-2.0.2.dist-info/RECORD
