Metadata-Version: 2.1
Name: ynab-api
Version: 2.0.2
Summary: YNAB API Endpoints
Home-page: 
Author: OpenAPI Generator community
Author-email: team@openapitools.org
Keywords: OpenAPI,OpenAPI-Generator,YNAB API Endpoints
Requires-Python: >=3.6
